<?xml version="1.0" encoding="utf-8"?>
<SoundBanksInfo Platform="Windows" BasePlatform="Windows" SchemaVersion="16" SoundBankVersion="150">
	<SoundBanks>
		<SoundBank Id="2765162312" Type="User" GUID="{9B915276-16F3-4721-B819-126344F97366}" Language="SFX" Hash="{38DF6B0C-5DA6-0E1F-211B-A583FE863BA9}">
			<ObjectPath>\SoundBanks\SoundBanks_WU\VOICES_SB</ObjectPath>
			<ShortName>VOICES_SB</ShortName>
			<Path>VOICES_SB.bnk</Path>
			<Media>
				<File Id="7231555" Language="SFX" Streaming="false" Location="Memory">
					<ShortName>DUB_ARENA_1_2_2.wav</ShortName>
					<CachePath>SFX/DUB_ARENA_1_2_2_818F3B66.wem</CachePath>
				</File>
				<File Id="12434701" Language="SFX" Streaming="false" Location="Memory">
					<ShortName>DUB_ALLY_1_3_0.wav</ShortName>
					<CachePath>SFX/DUB_ALLY_1_3_0_818F3B66.wem</CachePath>
				</File>
				<File Id="45960235" Language="SFX" Streaming="false" Location="Memory">
					<ShortName>DUB_ALLY_1_4_0.wav</ShortName>
					<CachePath>SFX/DUB_ALLY_1_4_0_B42FC9A2.wem</CachePath>
				</File>
				<File Id="73406871" Language="SFX" Streaming="false" Location="Memory">
					<ShortName>DUB_ARENA_1_7_0.wav</ShortName>
					<CachePath>SFX/DUB_ARENA_1_7_0_818F3B66.wem</CachePath>
				</File>
				<File Id="83922193" Language="SFX" Streaming="false" Location="Memory">
					<ShortName>DUB_ARENA_1_2_3.wav</ShortName>
					<CachePath>SFX/DUB_ARENA_1_2_3_818F3B66.wem</CachePath>
				</File>
				<File Id="84247758" Language="SFX" Streaming="false" Location="Memory">
					<ShortName>DUB_ALLY_1_8_0.wav</ShortName>
					<CachePath>SFX/DUB_ALLY_1_8_0_818F3B66.wem</CachePath>
				</File>
				<File Id="93564485" Language="SFX" Streaming="false" Location="Memory">
					<ShortName>DUB_ARENA_1_0_0.wav</ShortName>
					<CachePath>SFX/DUB_ARENA_1_0_0_818F3B66.wem</CachePath>
				</File>
				<File Id="115645254" Language="SFX" Streaming="false" Location="Memory">
					<ShortName>DUB_ARENA_1_9_4.wav</ShortName>
					<CachePath>SFX/DUB_ARENA_1_9_4_818F3B66.wem</CachePath>
				</File>
				<File Id="140616404" Language="SFX" Streaming="false" Location="Memory">
					<ShortName>DUB_ARENA_1_8_0.wav</ShortName>
					<CachePath>SFX/DUB_ARENA_1_8_0_818F3B66.wem</CachePath>
				</File>
				<File Id="157392684" Language="SFX" Streaming="false" Location="Memory">
					<ShortName>DUB_ARENA_1_9_2.wav</ShortName>
					<CachePath>SFX/DUB_ARENA_1_9_2_818F3B66.wem</CachePath>
				</File>
				<File Id="166584951" Language="SFX" Streaming="false" Location="Memory">
					<ShortName>DUB_ARENA_1_9_1.wav</ShortName>
					<CachePath>SFX/DUB_ARENA_1_9_1_818F3B66.wem</CachePath>
				</File>
				<File Id="199901849" Language="SFX" Streaming="false" Location="Memory">
					<ShortName>DUB_ALLY_1_2_0.wav</ShortName>
					<CachePath>SFX/DUB_ALLY_1_2_0_818F3B66.wem</CachePath>
				</File>
				<File Id="276376101" Language="SFX" Streaming="false" Location="Memory">
					<ShortName>DUB_ALLY_1_0_2.wav</ShortName>
					<CachePath>SFX/DUB_ALLY_1_0_2_818F3B66.wem</CachePath>
				</File>
				<File Id="278418833" Language="SFX" Streaming="false" Location="Memory">
					<ShortName>DUB_ARENA_1_9_3.wav</ShortName>
					<CachePath>SFX/DUB_ARENA_1_9_3_818F3B66.wem</CachePath>
				</File>
				<File Id="279456589" Language="SFX" Streaming="false" Location="Memory">
					<ShortName>DUB_ARENA_1_9_5.wav</ShortName>
					<CachePath>SFX/DUB_ARENA_1_9_5_818F3B66.wem</CachePath>
				</File>
				<File Id="289625457" Language="SFX" Streaming="false" Location="Memory">
					<ShortName>DUB_ARENA_1_3_0.wav</ShortName>
					<CachePath>SFX/DUB_ARENA_1_3_0_818F3B66.wem</CachePath>
				</File>
				<File Id="305437427" Language="SFX" Streaming="false" Location="Memory">
					<ShortName>DUB_ALLY_1_4_0.wav</ShortName>
					<CachePath>SFX/DUB_ALLY_1_4_0_E0C25F29.wem</CachePath>
				</File>
				<File Id="315927435" Language="SFX" Streaming="false" Location="Memory">
					<ShortName>DUB_ALLY_1_6_1.wav</ShortName>
					<CachePath>SFX/DUB_ALLY_1_6_1_818F3B66.wem</CachePath>
				</File>
				<File Id="338368799" Language="SFX" Streaming="false" Location="Memory">
					<ShortName>DUB_ARENA_1_1_2.wav</ShortName>
					<CachePath>SFX/DUB_ARENA_1_1_2_818F3B66.wem</CachePath>
				</File>
				<File Id="338492853" Language="SFX" Streaming="false" Location="Memory">
					<ShortName>DUB_ALLY_1_6_0.wav</ShortName>
					<CachePath>SFX/DUB_ALLY_1_6_0_818F3B66.wem</CachePath>
				</File>
				<File Id="381597154" Language="SFX" Streaming="false" Location="Memory">
					<ShortName>DUB_ALLY_1_1_0.wav</ShortName>
					<CachePath>SFX/DUB_ALLY_1_1_0_818F3B66.wem</CachePath>
				</File>
				<File Id="411650085" Language="SFX" Streaming="false" Location="Memory">
					<ShortName>DUB_ARENA_1_9_6.wav</ShortName>
					<CachePath>SFX/DUB_ARENA_1_9_6_818F3B66.wem</CachePath>
				</File>
				<File Id="435995496" Language="SFX" Streaming="false" Location="Memory">
					<ShortName>DUB_ARENA_1_6_0.wav</ShortName>
					<CachePath>SFX/DUB_ARENA_1_6_0_818F3B66.wem</CachePath>
				</File>
				<File Id="500906151" Language="SFX" Streaming="false" Location="Memory">
					<ShortName>DUB_ARENA_1_1_1.wav</ShortName>
					<CachePath>SFX/DUB_ARENA_1_1_1_818F3B66.wem</CachePath>
				</File>
				<File Id="675447814" Language="SFX" Streaming="false" Location="Memory">
					<ShortName>DUB_ALLY_1_0_0.wav</ShortName>
					<CachePath>SFX/DUB_ALLY_1_0_0_818F3B66.wem</CachePath>
				</File>
				<File Id="687283735" Language="SFX" Streaming="false" Location="Memory">
					<ShortName>DUB_ARENA_1_2_0.wav</ShortName>
					<CachePath>SFX/DUB_ARENA_1_2_0_818F3B66.wem</CachePath>
				</File>
				<File Id="700914992" Language="SFX" Streaming="false" Location="Memory">
					<ShortName>DUB_ALLY_1_0_1.wav</ShortName>
					<CachePath>SFX/DUB_ALLY_1_0_1_818F3B66.wem</CachePath>
				</File>
				<File Id="753350392" Language="SFX" Streaming="false" Location="Memory">
					<ShortName>DUB_ALLY_1_5_0.wav</ShortName>
					<CachePath>SFX/DUB_ALLY_1_5_0_818F3B66.wem</CachePath>
				</File>
				<File Id="767088532" Language="SFX" Streaming="false" Location="Memory">
					<ShortName>DUB_ARENA_1_9_0.wav</ShortName>
					<CachePath>SFX/DUB_ARENA_1_9_0_818F3B66.wem</CachePath>
				</File>
				<File Id="881110537" Language="SFX" Streaming="false" Location="Memory">
					<ShortName>DUB_ARENA_1_3_2.wav</ShortName>
					<CachePath>SFX/DUB_ARENA_1_3_2_818F3B66.wem</CachePath>
				</File>
				<File Id="898148885" Language="SFX" Streaming="false" Location="Memory">
					<ShortName>DUB_ARENA_1_1_0.wav</ShortName>
					<CachePath>SFX/DUB_ARENA_1_1_0_818F3B66.wem</CachePath>
				</File>
				<File Id="899907561" Language="SFX" Streaming="false" Location="Memory">
					<ShortName>DUB_ARENA_1_5_0.wav</ShortName>
					<CachePath>SFX/DUB_ARENA_1_5_0_818F3B66.wem</CachePath>
				</File>
				<File Id="952186329" Language="SFX" Streaming="false" Location="Memory">
					<ShortName>DUB_ARENA_1_4_0.wav</ShortName>
					<CachePath>SFX/DUB_ARENA_1_4_0_818F3B66.wem</CachePath>
				</File>
				<File Id="981954510" Language="SFX" Streaming="false" Location="Memory">
					<ShortName>DUB_ALLY_1_7_0.wav</ShortName>
					<CachePath>SFX/DUB_ALLY_1_7_0_818F3B66.wem</CachePath>
				</File>
				<File Id="1008445025" Language="SFX" Streaming="false" Location="Memory">
					<ShortName>DUB_ARENA_1_2_1.wav</ShortName>
					<CachePath>SFX/DUB_ARENA_1_2_1_818F3B66.wem</CachePath>
				</File>
				<File Id="1031568460" Language="SFX" Streaming="false" Location="Memory">
					<ShortName>DUB_ARENA_1_3_1.wav</ShortName>
					<CachePath>SFX/DUB_ARENA_1_3_1_818F3B66.wem</CachePath>
				</File>
			</Media>
			<Events>
				<Event Id="224580060" Name="Play_DUB_ALLY_1_0_0" ObjectPath="\Events\VOICES_WU\ALLY\Play_DUB_ALLY_1_0_0" GUID="{9F96A97A-7CD0-40FE-8F5A-DBC3B18BA896}" DurationType="OneShot" DurationMin="6.7155595" DurationMax="6.7155595">
					<MediaRefs>
						<MediaRef Id="675447814"/>
					</MediaRefs>
				</Event>
				<Event Id="224580061" Name="Play_DUB_ALLY_1_0_1" ObjectPath="\Events\VOICES_WU\ALLY\Play_DUB_ALLY_1_0_1" GUID="{2A374C83-3AF0-4BA0-8A14-901DA3F2F6DC}" DurationType="OneShot" DurationMin="4.883933" DurationMax="4.883933">
					<MediaRefs>
						<MediaRef Id="700914992"/>
					</MediaRefs>
				</Event>
				<Event Id="224580062" Name="Play_DUB_ALLY_1_0_2" ObjectPath="\Events\VOICES_WU\ALLY\Play_DUB_ALLY_1_0_2" GUID="{3713AC7A-830D-4D17-BBDE-B07E086AC0EA}" DurationType="OneShot" DurationMin="8.468875" DurationMax="8.468875">
					<MediaRefs>
						<MediaRef Id="276376101"/>
					</MediaRefs>
				</Event>
				<Event Id="224432997" Name="Play_DUB_ALLY_1_1_0" ObjectPath="\Events\VOICES_WU\ALLY\Play_DUB_ALLY_1_1_0" GUID="{E89BD675-9B49-4310-B78F-A95B7FF89CE1}" DurationType="OneShot" DurationMin="4.5633903" DurationMax="4.5633903">
					<MediaRefs>
						<MediaRef Id="381597154"/>
					</MediaRefs>
				</Event>
				<Event Id="224874282" Name="Play_DUB_ALLY_1_2_0" ObjectPath="\Events\VOICES_WU\ALLY\Play_DUB_ALLY_1_2_0" GUID="{65109B34-CC45-4D18-A9FE-36DBD194EFC8}" DurationType="OneShot" DurationMin="2.5934453" DurationMax="2.5934453">
					<MediaRefs>
						<MediaRef Id="199901849"/>
					</MediaRefs>
				</Event>
				<Event Id="3445926899" Name="Play_DUB_ALLY_1_3_0" ObjectPath="\Events\VOICES_WU\ALLY\Play_DUB_ALLY_1_3_0" GUID="{E8053C0C-DFBF-470A-91FC-BE37A0718140}" DurationType="OneShot" DurationMin="3.9183755" DurationMax="3.9183755">
					<MediaRefs>
						<MediaRef Id="12434701"/>
					</MediaRefs>
				</Event>
				<Event Id="3446471352" Name="Play_DUB_ALLY_1_4_0" ObjectPath="\Events\VOICES_WU\ALLY\Play_DUB_ALLY_1_4_0" GUID="{E1F85B8A-4F18-4DB3-8AE4-F7660419F33F}" DurationType="OneShot" DurationMin="1.269327" DurationMax="1.269327">
					<MediaRefs>
						<MediaRef Id="305437427"/>
					</MediaRefs>
				</Event>
				<Event Id="3446471353" Name="Play_DUB_ALLY_1_4_1" ObjectPath="\Events\VOICES_WU\ALLY\Play_DUB_ALLY_1_4_1" GUID="{C3297B53-25D6-4948-8D75-CBAAD1EC4D31}" DurationType="OneShot" DurationMin="1.8102334" DurationMax="1.8102334">
					<MediaRefs>
						<MediaRef Id="45960235"/>
					</MediaRefs>
				</Event>
				<Event Id="225021313" Name="Play_DUB_ALLY_1_5_0" ObjectPath="\Events\VOICES_WU\ALLY\Play_DUB_ALLY_1_5_0" GUID="{98283835-5A72-485F-BC7F-D1FE516F0BED}" DurationType="OneShot" DurationMin="6.907216" DurationMax="6.907216">
					<MediaRefs>
						<MediaRef Id="753350392"/>
					</MediaRefs>
				</Event>
				<Event Id="225565766" Name="Play_DUB_ALLY_1_6_0" ObjectPath="\Events\VOICES_WU\ALLY\Play_DUB_ALLY_1_6_0" GUID="{4385C1FA-94CC-437A-AD35-153210E76491}" DurationType="OneShot" DurationMin="3.6959293" DurationMax="3.6959293">
					<MediaRefs>
						<MediaRef Id="338492853"/>
					</MediaRefs>
				</Event>
				<Event Id="225565767" Name="Play_DUB_ALLY_1_6_1" ObjectPath="\Events\VOICES_WU\ALLY\Play_DUB_ALLY_1_6_1" GUID="{081FB818-BCA9-4AB7-8B96-799941566E22}" DurationType="OneShot" DurationMin="0.98509604" DurationMax="0.98509604">
					<MediaRefs>
						<MediaRef Id="315927435"/>
					</MediaRefs>
				</Event>
				<Event Id="3446618415" Name="Play_DUB_ALLY_1_7_0" ObjectPath="\Events\VOICES_WU\ALLY\Play_DUB_ALLY_1_7_0" GUID="{597D5DD9-17B4-4440-8CC0-486223252911}" DurationType="OneShot" DurationMin="7.1776547" DurationMax="7.1776547">
					<MediaRefs>
						<MediaRef Id="981954510"/>
					</MediaRefs>
				</Event>
				<Event Id="223300100" Name="Play_DUB_ALLY_1_8_0" ObjectPath="\Events\VOICES_WU\ALLY\Play_DUB_ALLY_1_8_0" GUID="{BD6DFD3A-46D9-48FB-AF2A-0FA3E604A037}" DurationType="OneShot" DurationMin="4.7907324" DurationMax="4.7907324">
					<MediaRefs>
						<MediaRef Id="84247758"/>
					</MediaRefs>
				</Event>
				<Event Id="3653177071" Name="Play_DUB_ARENA_1_0_0" ObjectPath="\Events\VOICES_WU\ARENA\Play_DUB_ARENA_1_0_0" GUID="{6CB2E320-5F3F-4792-B1C8-029B1D05BDA8}" DurationType="OneShot" DurationMin="11.3325205" DurationMax="11.3325205">
					<MediaRefs>
						<MediaRef Id="93564485"/>
					</MediaRefs>
					<AuxBusRefs>
						<AuxBusRef Id="367558429" Name="RVB_Voices" ObjectPath="\Master-Mixer Hierarchy\Master_WU\Master\RVB_Voices" GUID="{483EAB60-BC92-484F-9830-D1776233B15C}"/>
						<AuxBusRef Id="2561323002" Name="AUX_LPF" ObjectPath="\Master-Mixer Hierarchy\Master_WU\Master\AUX_LPF" GUID="{5D5AAEA6-57CB-46FD-9802-C041695A5809}"/>
					</AuxBusRefs>
				</Event>
				<Event Id="432124422" Name="Play_DUB_ARENA_1_1_0" ObjectPath="\Events\VOICES_WU\ARENA\Play_DUB_ARENA_1_1_0" GUID="{4D51FF6E-B699-4F64-9342-EA27E6FB1544}" DurationType="OneShot" DurationMin="5.3754582" DurationMax="5.3754582">
					<MediaRefs>
						<MediaRef Id="898148885"/>
					</MediaRefs>
					<AuxBusRefs>
						<AuxBusRef Id="367558429" Name="RVB_Voices" ObjectPath="\Master-Mixer Hierarchy\Master_WU\Master\RVB_Voices" GUID="{483EAB60-BC92-484F-9830-D1776233B15C}"/>
						<AuxBusRef Id="2561323002" Name="AUX_LPF" ObjectPath="\Master-Mixer Hierarchy\Master_WU\Master\AUX_LPF" GUID="{5D5AAEA6-57CB-46FD-9802-C041695A5809}"/>
					</AuxBusRefs>
				</Event>
				<Event Id="432124423" Name="Play_DUB_ARENA_1_1_1" ObjectPath="\Events\VOICES_WU\ARENA\Play_DUB_ARENA_1_1_1" GUID="{27536445-6BFB-41C6-BC9E-54347C22D514}" DurationType="OneShot" DurationMin="2.5813334" DurationMax="2.5813334">
					<MediaRefs>
						<MediaRef Id="500906151"/>
					</MediaRefs>
					<AuxBusRefs>
						<AuxBusRef Id="367558429" Name="RVB_Voices" ObjectPath="\Master-Mixer Hierarchy\Master_WU\Master\RVB_Voices" GUID="{483EAB60-BC92-484F-9830-D1776233B15C}"/>
						<AuxBusRef Id="2561323002" Name="AUX_LPF" ObjectPath="\Master-Mixer Hierarchy\Master_WU\Master\AUX_LPF" GUID="{5D5AAEA6-57CB-46FD-9802-C041695A5809}"/>
					</AuxBusRefs>
				</Event>
				<Event Id="432124420" Name="Play_DUB_ARENA_1_1_2" ObjectPath="\Events\VOICES_WU\ARENA\Play_DUB_ARENA_1_1_2" GUID="{DE0F7AE6-9779-495E-AA81-79548E94F86D}" DurationType="OneShot" DurationMin="2.7846458" DurationMax="2.7846458">
					<MediaRefs>
						<MediaRef Id="338368799"/>
					</MediaRefs>
					<AuxBusRefs>
						<AuxBusRef Id="367558429" Name="RVB_Voices" ObjectPath="\Master-Mixer Hierarchy\Master_WU\Master\RVB_Voices" GUID="{483EAB60-BC92-484F-9830-D1776233B15C}"/>
						<AuxBusRef Id="2561323002" Name="AUX_LPF" ObjectPath="\Master-Mixer Hierarchy\Master_WU\Master\AUX_LPF" GUID="{5D5AAEA6-57CB-46FD-9802-C041695A5809}"/>
					</AuxBusRefs>
				</Event>
				<Event Id="431683137" Name="Play_DUB_ARENA_1_2_0" ObjectPath="\Events\VOICES_WU\ARENA\Play_DUB_ARENA_1_2_0" GUID="{C445715B-3FA8-4FBC-AB70-822C92FBB16B}" DurationType="OneShot" DurationMin="3.629021" DurationMax="3.629021">
					<MediaRefs>
						<MediaRef Id="687283735"/>
					</MediaRefs>
					<AuxBusRefs>
						<AuxBusRef Id="367558429" Name="RVB_Voices" ObjectPath="\Master-Mixer Hierarchy\Master_WU\Master\RVB_Voices" GUID="{483EAB60-BC92-484F-9830-D1776233B15C}"/>
						<AuxBusRef Id="2561323002" Name="AUX_LPF" ObjectPath="\Master-Mixer Hierarchy\Master_WU\Master\AUX_LPF" GUID="{5D5AAEA6-57CB-46FD-9802-C041695A5809}"/>
					</AuxBusRefs>
				</Event>
				<Event Id="431683136" Name="Play_DUB_ARENA_1_2_1" ObjectPath="\Events\VOICES_WU\ARENA\Play_DUB_ARENA_1_2_1" GUID="{91178517-FD31-404C-BD96-C93C088E3CC4}" DurationType="OneShot" DurationMin="3.111125" DurationMax="3.111125">
					<MediaRefs>
						<MediaRef Id="1008445025"/>
					</MediaRefs>
					<AuxBusRefs>
						<AuxBusRef Id="367558429" Name="RVB_Voices" ObjectPath="\Master-Mixer Hierarchy\Master_WU\Master\RVB_Voices" GUID="{483EAB60-BC92-484F-9830-D1776233B15C}"/>
						<AuxBusRef Id="2561323002" Name="AUX_LPF" ObjectPath="\Master-Mixer Hierarchy\Master_WU\Master\AUX_LPF" GUID="{5D5AAEA6-57CB-46FD-9802-C041695A5809}"/>
					</AuxBusRefs>
				</Event>
				<Event Id="431683139" Name="Play_DUB_ARENA_1_2_2" ObjectPath="\Events\VOICES_WU\ARENA\Play_DUB_ARENA_1_2_2" GUID="{746849AC-4863-4498-9421-326BA34079B6}" DurationType="OneShot" DurationMin="5.2867084" DurationMax="5.2867084">
					<MediaRefs>
						<MediaRef Id="7231555"/>
					</MediaRefs>
					<AuxBusRefs>
						<AuxBusRef Id="367558429" Name="RVB_Voices" ObjectPath="\Master-Mixer Hierarchy\Master_WU\Master\RVB_Voices" GUID="{483EAB60-BC92-484F-9830-D1776233B15C}"/>
						<AuxBusRef Id="2561323002" Name="AUX_LPF" ObjectPath="\Master-Mixer Hierarchy\Master_WU\Master\AUX_LPF" GUID="{5D5AAEA6-57CB-46FD-9802-C041695A5809}"/>
					</AuxBusRefs>
				</Event>
				<Event Id="431683138" Name="Play_DUB_ARENA_1_2_3" ObjectPath="\Events\VOICES_WU\ARENA\Play_DUB_ARENA_1_2_3" GUID="{2CE4857B-BB5A-42DF-B161-ABAB474C8636}" DurationType="OneShot" DurationMin="5.847521" DurationMax="5.847521">
					<MediaRefs>
						<MediaRef Id="83922193"/>
					</MediaRefs>
					<AuxBusRefs>
						<AuxBusRef Id="367558429" Name="RVB_Voices" ObjectPath="\Master-Mixer Hierarchy\Master_WU\Master\RVB_Voices" GUID="{483EAB60-BC92-484F-9830-D1776233B15C}"/>
						<AuxBusRef Id="2561323002" Name="AUX_LPF" ObjectPath="\Master-Mixer Hierarchy\Master_WU\Master\AUX_LPF" GUID="{5D5AAEA6-57CB-46FD-9802-C041695A5809}"/>
					</AuxBusRefs>
				</Event>
				<Event Id="3653030008" Name="Play_DUB_ARENA_1_3_0" ObjectPath="\Events\VOICES_WU\ARENA\Play_DUB_ARENA_1_3_0" GUID="{D4B8EC1E-8BCC-47F8-BDCC-CE8B7FC3ED1C}" DurationType="OneShot" DurationMin="6.983125" DurationMax="6.983125">
					<MediaRefs>
						<MediaRef Id="289625457"/>
					</MediaRefs>
					<AuxBusRefs>
						<AuxBusRef Id="367558429" Name="RVB_Voices" ObjectPath="\Master-Mixer Hierarchy\Master_WU\Master\RVB_Voices" GUID="{483EAB60-BC92-484F-9830-D1776233B15C}"/>
						<AuxBusRef Id="2561323002" Name="AUX_LPF" ObjectPath="\Master-Mixer Hierarchy\Master_WU\Master\AUX_LPF" GUID="{5D5AAEA6-57CB-46FD-9802-C041695A5809}"/>
					</AuxBusRefs>
				</Event>
				<Event Id="3653030009" Name="Play_DUB_ARENA_1_3_1" ObjectPath="\Events\VOICES_WU\ARENA\Play_DUB_ARENA_1_3_1" GUID="{D97FF8EC-ED87-4915-9E9E-1C708E08A828}" DurationType="OneShot" DurationMin="3.3593957" DurationMax="3.3593957">
					<MediaRefs>
						<MediaRef Id="1031568460"/>
					</MediaRefs>
					<AuxBusRefs>
						<AuxBusRef Id="367558429" Name="RVB_Voices" ObjectPath="\Master-Mixer Hierarchy\Master_WU\Master\RVB_Voices" GUID="{483EAB60-BC92-484F-9830-D1776233B15C}"/>
						<AuxBusRef Id="2561323002" Name="AUX_LPF" ObjectPath="\Master-Mixer Hierarchy\Master_WU\Master\AUX_LPF" GUID="{5D5AAEA6-57CB-46FD-9802-C041695A5809}"/>
					</AuxBusRefs>
				</Event>
				<Event Id="3653030010" Name="Play_DUB_ARENA_1_3_2" ObjectPath="\Events\VOICES_WU\ARENA\Play_DUB_ARENA_1_3_2" GUID="{0746558A-9F04-4B0B-B346-9BA6CF66D24C}" DurationType="OneShot" DurationMin="7.75375" DurationMax="7.75375">
					<MediaRefs>
						<MediaRef Id="881110537"/>
					</MediaRefs>
					<AuxBusRefs>
						<AuxBusRef Id="367558429" Name="RVB_Voices" ObjectPath="\Master-Mixer Hierarchy\Master_WU\Master\RVB_Voices" GUID="{483EAB60-BC92-484F-9830-D1776233B15C}"/>
						<AuxBusRef Id="2561323002" Name="AUX_LPF" ObjectPath="\Master-Mixer Hierarchy\Master_WU\Master\AUX_LPF" GUID="{5D5AAEA6-57CB-46FD-9802-C041695A5809}"/>
					</AuxBusRefs>
				</Event>
				<Event Id="3652588723" Name="Play_DUB_ARENA_1_4_0" ObjectPath="\Events\VOICES_WU\ARENA\Play_DUB_ARENA_1_4_0" GUID="{809EBE6E-E883-4D44-87C4-923BF4435E0D}" DurationType="OneShot" DurationMin="8.455104" DurationMax="8.455104">
					<MediaRefs>
						<MediaRef Id="952186329"/>
					</MediaRefs>
					<AuxBusRefs>
						<AuxBusRef Id="367558429" Name="RVB_Voices" ObjectPath="\Master-Mixer Hierarchy\Master_WU\Master\RVB_Voices" GUID="{483EAB60-BC92-484F-9830-D1776233B15C}"/>
						<AuxBusRef Id="2561323002" Name="AUX_LPF" ObjectPath="\Master-Mixer Hierarchy\Master_WU\Master\AUX_LPF" GUID="{5D5AAEA6-57CB-46FD-9802-C041695A5809}"/>
					</AuxBusRefs>
				</Event>
				<Event Id="431536106" Name="Play_DUB_ARENA_1_5_0" ObjectPath="\Events\VOICES_WU\ARENA\Play_DUB_ARENA_1_5_0" GUID="{2945E4E8-A2EB-4D65-B4D4-F7738BA67018}" DurationType="OneShot" DurationMin="4.879229" DurationMax="4.879229">
					<MediaRefs>
						<MediaRef Id="899907561"/>
					</MediaRefs>
					<AuxBusRefs>
						<AuxBusRef Id="367558429" Name="RVB_Voices" ObjectPath="\Master-Mixer Hierarchy\Master_WU\Master\RVB_Voices" GUID="{483EAB60-BC92-484F-9830-D1776233B15C}"/>
						<AuxBusRef Id="2561323002" Name="AUX_LPF" ObjectPath="\Master-Mixer Hierarchy\Master_WU\Master\AUX_LPF" GUID="{5D5AAEA6-57CB-46FD-9802-C041695A5809}"/>
					</AuxBusRefs>
				</Event>
				<Event Id="430991653" Name="Play_DUB_ARENA_1_6_0" ObjectPath="\Events\VOICES_WU\ARENA\Play_DUB_ARENA_1_6_0" GUID="{5A59BF8D-9B94-480D-A8BE-25466AFDDDAF}" DurationType="OneShot" DurationMin="10.083875" DurationMax="10.083875">
					<MediaRefs>
						<MediaRef Id="435995496"/>
					</MediaRefs>
					<AuxBusRefs>
						<AuxBusRef Id="367558429" Name="RVB_Voices" ObjectPath="\Master-Mixer Hierarchy\Master_WU\Master\RVB_Voices" GUID="{483EAB60-BC92-484F-9830-D1776233B15C}"/>
						<AuxBusRef Id="2561323002" Name="AUX_LPF" ObjectPath="\Master-Mixer Hierarchy\Master_WU\Master\AUX_LPF" GUID="{5D5AAEA6-57CB-46FD-9802-C041695A5809}"/>
					</AuxBusRefs>
				</Event>
				<Event Id="431138716" Name="Play_DUB_ARENA_1_7_0" ObjectPath="\Events\VOICES_WU\ARENA\Play_DUB_ARENA_1_7_0" GUID="{F6358FF6-964A-43B2-B731-095E10582A7A}" DurationType="OneShot" DurationMin="4.7953334" DurationMax="4.7953334">
					<MediaRefs>
						<MediaRef Id="73406871"/>
					</MediaRefs>
					<AuxBusRefs>
						<AuxBusRef Id="367558429" Name="RVB_Voices" ObjectPath="\Master-Mixer Hierarchy\Master_WU\Master\RVB_Voices" GUID="{483EAB60-BC92-484F-9830-D1776233B15C}"/>
						<AuxBusRef Id="2561323002" Name="AUX_LPF" ObjectPath="\Master-Mixer Hierarchy\Master_WU\Master\AUX_LPF" GUID="{5D5AAEA6-57CB-46FD-9802-C041695A5809}"/>
					</AuxBusRefs>
				</Event>
				<Event Id="3651897111" Name="Play_DUB_ARENA_1_8_0" ObjectPath="\Events\VOICES_WU\ARENA\Play_DUB_ARENA_1_8_0" GUID="{6C548FEA-C807-4A6A-B0D6-C9C265D28446}" DurationType="OneShot" DurationMin="5.6705" DurationMax="5.6705">
					<MediaRefs>
						<MediaRef Id="140616404"/>
					</MediaRefs>
					<AuxBusRefs>
						<AuxBusRef Id="367558429" Name="RVB_Voices" ObjectPath="\Master-Mixer Hierarchy\Master_WU\Master\RVB_Voices" GUID="{483EAB60-BC92-484F-9830-D1776233B15C}"/>
						<AuxBusRef Id="2561323002" Name="AUX_LPF" ObjectPath="\Master-Mixer Hierarchy\Master_WU\Master\AUX_LPF" GUID="{5D5AAEA6-57CB-46FD-9802-C041695A5809}"/>
					</AuxBusRefs>
				</Event>
				<Event Id="3652044174" Name="Play_DUB_ARENA_1_9_0" ObjectPath="\Events\VOICES_WU\ARENA\Play_DUB_ARENA_1_9_0" GUID="{EFF04B34-33D4-45A1-B15C-C75DF1C2FE84}" DurationType="OneShot" DurationMin="2.0564792" DurationMax="2.0564792">
					<MediaRefs>
						<MediaRef Id="767088532"/>
					</MediaRefs>
					<AuxBusRefs>
						<AuxBusRef Id="367558429" Name="RVB_Voices" ObjectPath="\Master-Mixer Hierarchy\Master_WU\Master\RVB_Voices" GUID="{483EAB60-BC92-484F-9830-D1776233B15C}"/>
						<AuxBusRef Id="2561323002" Name="AUX_LPF" ObjectPath="\Master-Mixer Hierarchy\Master_WU\Master\AUX_LPF" GUID="{5D5AAEA6-57CB-46FD-9802-C041695A5809}"/>
					</AuxBusRefs>
				</Event>
				<Event Id="3652044175" Name="Play_DUB_ARENA_1_9_1" ObjectPath="\Events\VOICES_WU\ARENA\Play_DUB_ARENA_1_9_1" GUID="{80641E23-366E-4E92-9C60-75DC0F6F4B16}" DurationType="OneShot" DurationMin="3.72625" DurationMax="3.72625">
					<MediaRefs>
						<MediaRef Id="166584951"/>
					</MediaRefs>
					<AuxBusRefs>
						<AuxBusRef Id="367558429" Name="RVB_Voices" ObjectPath="\Master-Mixer Hierarchy\Master_WU\Master\RVB_Voices" GUID="{483EAB60-BC92-484F-9830-D1776233B15C}"/>
						<AuxBusRef Id="2561323002" Name="AUX_LPF" ObjectPath="\Master-Mixer Hierarchy\Master_WU\Master\AUX_LPF" GUID="{5D5AAEA6-57CB-46FD-9802-C041695A5809}"/>
					</AuxBusRefs>
				</Event>
				<Event Id="3652044172" Name="Play_DUB_ARENA_1_9_2" ObjectPath="\Events\VOICES_WU\ARENA\Play_DUB_ARENA_1_9_2" GUID="{EADA4396-85FC-46B2-90D0-883FFB9406F7}" DurationType="OneShot" DurationMin="0.73702085" DurationMax="0.73702085">
					<MediaRefs>
						<MediaRef Id="157392684"/>
					</MediaRefs>
					<AuxBusRefs>
						<AuxBusRef Id="367558429" Name="RVB_Voices" ObjectPath="\Master-Mixer Hierarchy\Master_WU\Master\RVB_Voices" GUID="{483EAB60-BC92-484F-9830-D1776233B15C}"/>
						<AuxBusRef Id="2561323002" Name="AUX_LPF" ObjectPath="\Master-Mixer Hierarchy\Master_WU\Master\AUX_LPF" GUID="{5D5AAEA6-57CB-46FD-9802-C041695A5809}"/>
					</AuxBusRefs>
				</Event>
				<Event Id="3652044173" Name="Play_DUB_ARENA_1_9_3" ObjectPath="\Events\VOICES_WU\ARENA\Play_DUB_ARENA_1_9_3" GUID="{1D57409D-4D8B-4606-B981-BDD320FD64EB}" DurationType="OneShot" DurationMin="0.8344167" DurationMax="0.8344167">
					<MediaRefs>
						<MediaRef Id="278418833"/>
					</MediaRefs>
					<AuxBusRefs>
						<AuxBusRef Id="367558429" Name="RVB_Voices" ObjectPath="\Master-Mixer Hierarchy\Master_WU\Master\RVB_Voices" GUID="{483EAB60-BC92-484F-9830-D1776233B15C}"/>
						<AuxBusRef Id="2561323002" Name="AUX_LPF" ObjectPath="\Master-Mixer Hierarchy\Master_WU\Master\AUX_LPF" GUID="{5D5AAEA6-57CB-46FD-9802-C041695A5809}"/>
					</AuxBusRefs>
				</Event>
				<Event Id="3652044170" Name="Play_DUB_ARENA_1_9_4" ObjectPath="\Events\VOICES_WU\ARENA\Play_DUB_ARENA_1_9_4" GUID="{56D08A81-9E18-4348-AB5F-9AD1B9C7E045}" DurationType="OneShot" DurationMin="1.1080834" DurationMax="1.1080834">
					<MediaRefs>
						<MediaRef Id="115645254"/>
					</MediaRefs>
					<AuxBusRefs>
						<AuxBusRef Id="367558429" Name="RVB_Voices" ObjectPath="\Master-Mixer Hierarchy\Master_WU\Master\RVB_Voices" GUID="{483EAB60-BC92-484F-9830-D1776233B15C}"/>
						<AuxBusRef Id="2561323002" Name="AUX_LPF" ObjectPath="\Master-Mixer Hierarchy\Master_WU\Master\AUX_LPF" GUID="{5D5AAEA6-57CB-46FD-9802-C041695A5809}"/>
					</AuxBusRefs>
				</Event>
				<Event Id="3652044171" Name="Play_DUB_ARENA_1_9_5" ObjectPath="\Events\VOICES_WU\ARENA\Play_DUB_ARENA_1_9_5" GUID="{6C020C9C-BAF0-41AB-9564-CAFCF453F546}" DurationType="OneShot" DurationMin="2.2469792" DurationMax="2.2469792">
					<MediaRefs>
						<MediaRef Id="279456589"/>
					</MediaRefs>
					<AuxBusRefs>
						<AuxBusRef Id="367558429" Name="RVB_Voices" ObjectPath="\Master-Mixer Hierarchy\Master_WU\Master\RVB_Voices" GUID="{483EAB60-BC92-484F-9830-D1776233B15C}"/>
						<AuxBusRef Id="2561323002" Name="AUX_LPF" ObjectPath="\Master-Mixer Hierarchy\Master_WU\Master\AUX_LPF" GUID="{5D5AAEA6-57CB-46FD-9802-C041695A5809}"/>
					</AuxBusRefs>
				</Event>
				<Event Id="3652044168" Name="Play_DUB_ARENA_1_9_6" ObjectPath="\Events\VOICES_WU\ARENA\Play_DUB_ARENA_1_9_6" GUID="{1EBCCAD9-8483-4BE3-AFBC-EA3F1550B975}" DurationType="OneShot" DurationMin="4.590271" DurationMax="4.590271">
					<MediaRefs>
						<MediaRef Id="411650085"/>
					</MediaRefs>
					<AuxBusRefs>
						<AuxBusRef Id="367558429" Name="RVB_Voices" ObjectPath="\Master-Mixer Hierarchy\Master_WU\Master\RVB_Voices" GUID="{483EAB60-BC92-484F-9830-D1776233B15C}"/>
						<AuxBusRef Id="2561323002" Name="AUX_LPF" ObjectPath="\Master-Mixer Hierarchy\Master_WU\Master\AUX_LPF" GUID="{5D5AAEA6-57CB-46FD-9802-C041695A5809}"/>
					</AuxBusRefs>
				</Event>
			</Events>
		</SoundBank>
	</SoundBanks>
	<FileHash>{87B42577-F86D-CF64-1C87-C94821EAF329}</FileHash>
</SoundBanksInfo>
